future_thread.py
future_thread-1.0.dist-info/DESCRIPTION.rst
future_thread-1.0.dist-info/METADATA
future_thread-1.0.dist-info/RECORD
future_thread-1.0.dist-info/WHEEL
future_thread-1.0.dist-info/metadata.json
future_thread-1.0.dist-info/top_level.txt
