Metadata-Version: 2.0
Name: future-thread
Version: 1.0
Summary: A simple module for creating a background thread and returning a Future object
Home-page: https://gitlab.com/alelec/future_thread
Author: Andrew Leech
Author-email: andrew@alelec.net
License: UNKNOWN
Platform: UNKNOWN
